LICENSE
utinni/__init__.py
utinni-0.5.0.dist-info/LICENSE
utinni-0.5.0.dist-info/WHEEL
utinni-0.5.0.dist-info/METADATA
utinni-0.5.0.dist-info/RECORD
