Metadata-Version: 2.1
Name: utinni
Version: 0.5.0
Summary: Async client library for Empire's RESTful API 
Home-page: https://github.com/byt3bl33d3r/Utinni
License: GPL-3.0-only
Author: Marcello Salvati
Author-email: byt3bl33d3r@pm.me
Requires-Python: >=3.8.0,<4.0.0
Classifier: Environment :: Console
Classifier: License :: OSI Approved :: GNU General Public License v3 (GPLv3)
Classifier: Programming Language :: Python :: 3
Classifier: Programming Language :: Python :: 3.8
Classifier: Programming Language :: Python :: 3.9
Classifier: Topic :: Security
Requires-Dist: httpx (>=0.16.1,<0.17.0)
Project-URL: Repository, https://github.com/byt3bl33d3r/Utinni
